nebuloid/__init__.py
nebuloid/api/__init__.py
nebuloid/api/api.py
nebuloid/api/auth.py
nebuloid/api/context.py
nebuloid/api/data.py
nebuloid/api/expose_api.py
nebuloid/builder/__init__.py
nebuloid/builder/builder.py
nebuloid/core/__init__.py
nebuloid/core/access.py
nebuloid/core/core.py
nebuloid/core/server.py
nebuloid/core/services.py
nebuloid/core/storage.py
nebuloid/manifest/__init__.py
nebuloid/manifest/manifest.py
nebuloid/orm/__init__.py
nebuloid/orm/orm.py
nebuloid/orm/orm_models.py
nebuloid/plugins/__init__.py
nebuloid/plugins/manager.py
nebuloid/plugins/navbar/__init__.py
nebuloid/plugins/navbar/navbar.py
nebuloid/utils/auth.js
nebuloid/utils/tools.js
nebuloid/utils/template/pem.js.jinja
nebuloid/utils/template/portal.js.jinja
nebuloid-1.0.5.dist-info/METADATA
nebuloid-1.0.5.dist-info/WHEEL
nebuloid-1.0.5.dist-info/top_level.txt
nebuloid-1.0.5.dist-info/RECORD
