Metadata-Version: 2.4
Name: nebuloid
Version: 1.0.5
Summary: A modular Flask-based framework for rapid web app development.
Author-email: Sarvin <your@email.com>
License: MIT
Project-URL: Homepage, https://github.com/sxrvinzx/nebuloid
Project-URL: Source, https://github.com/sxrvinzx/nebuloid
Requires-Python: >=3.8
Requires-Dist: quart
Requires-Dist: sqlalchemy>=2.0
Requires-Dist: werkzeug
